README.md
setup.py
InformationRetrieval/__init__.py
InformationRetrieval/Document/AbstractCollection.py
InformationRetrieval/Document/DiskCollection.py
InformationRetrieval/Document/Document.py
InformationRetrieval/Document/DocumentText.py
InformationRetrieval/Document/DocumentType.py
InformationRetrieval/Document/DocumentWeighting.py
InformationRetrieval/Document/IndexType.py
InformationRetrieval/Document/LargeCollection.py
InformationRetrieval/Document/MediumCollection.py
InformationRetrieval/Document/MemoryCollection.py
InformationRetrieval/Document/Parameter.py
InformationRetrieval/Document/__init__.py
InformationRetrieval/Index/CategoryNode.py
InformationRetrieval/Index/CategoryTree.py
InformationRetrieval/Index/IncidenceMatrix.py
InformationRetrieval/Index/InvertedIndex.py
InformationRetrieval/Index/NGramIndex.py
InformationRetrieval/Index/PositionalIndex.py
InformationRetrieval/Index/PositionalPosting.py
InformationRetrieval/Index/PositionalPostingList.py
InformationRetrieval/Index/Posting.py
InformationRetrieval/Index/PostingList.py
InformationRetrieval/Index/PostingSkip.py
InformationRetrieval/Index/PostingSkipList.py
InformationRetrieval/Index/Term.py
InformationRetrieval/Index/TermDictionary.py
InformationRetrieval/Index/TermOccurrence.py
InformationRetrieval/Index/TermType.py
InformationRetrieval/Index/TermWeighting.py
InformationRetrieval/Index/__init__.py
InformationRetrieval/Query/CategoryDeterminationType.py
InformationRetrieval/Query/FocusType.py
InformationRetrieval/Query/Query.py
InformationRetrieval/Query/QueryResult.py
InformationRetrieval/Query/QueryResultItem.py
InformationRetrieval/Query/RetrievalType.py
InformationRetrieval/Query/SearchParameter.py
InformationRetrieval/Query/VectorSpaceModel.py
InformationRetrieval/Query/__init__.py
NlpToolkit_InformationRetrieval.egg-info/PKG-INFO
NlpToolkit_InformationRetrieval.egg-info/SOURCES.txt
NlpToolkit_InformationRetrieval.egg-info/dependency_links.txt
NlpToolkit_InformationRetrieval.egg-info/requires.txt
NlpToolkit_InformationRetrieval.egg-info/top_level.txt