Metadata-Version: 2.1
Name: NlpToolkit-InformationRetrieval
Version: 1.0.6
Summary: Information Retrieval Library
Home-page: https://github.com/StarlangSoftware/InformationRetrieval-Py
Author: olcaytaner
Author-email: olcay.yildiz@ozyegin.edu.tr
License: UNKNOWN
Platform: UNKNOWN
